README.rst
setup.py
average/__init__.py
average/ewma.py
average/pdma.py
average.egg-info/PKG-INFO
average.egg-info/SOURCES.txt
average.egg-info/dependency_links.txt
average.egg-info/requires.txt
average.egg-info/top_level.txt