Metadata-Version: 1.1
Name: average
Version: 1.0
Summary: Moving averaging schemes (exponentially weighted, polynomial-decay).
Home-page: https://github.com/crowsonkb/average
Author: Katherine Crowson
Author-email: crowsonkb@gmail.com
License: MIT
Platform: UNKNOWN
Classifier: Development Status :: 5 - Production/Stable
Classifier: Intended Audience :: Developers
Classifier: License :: OSI Approved :: MIT License
Classifier: Programming Language :: Python :: 3.6
Classifier: Programming Language :: Python :: 3.7
Classifier: Topic :: Scientific/Engineering :: Mathematics
